[
  {
    "firstName": "test",
    "lastName": "user",
    "email": "test@user.com",
    "password": "password",
    "companyName": "new",
    "id": "3a821cb6-aa73-4ab7-95d1-19cfa6e35ef5",
    "createdAt": "2025-11-27T18:03:38.5866579"
  },
  {
    "firstName": "test",
    "lastName": "user",
    "email": "test@user.com",
    "password": "password",
    "companyName": "New",
    "id": "db689445-45db-4cac-9407-9d36a8cdd879",
    "createdAt": "2025-11-27T18:08:56.5546649"
  },
  {
    "firstName": "test",
    "lastName": "user",
    "email": "test@user.com",
    "password": "password",
    "companyName": "New",
    "id": "4c67869a-a981-49f9-a6e1-a9083824d1a3",
    "createdAt": "2025-11-27T18:16:00.8969326"
  },
  {
    "firstName": "test",
    "lastName": "user",
    "email": "test@user.com",
    "password": "password",
    "companyName": "New",
    "id": "4c769ad5-b3ed-4533-8608-d32044ab036b",
    "createdAt": "2025-11-27T18:21:29.750427"
  },
  {
    "firstName": "test",
    "lastName": "user",
    "email": "test@user.com",
    "password": "password",
    "companyName": "New",
    "id": "ff12afbc-4a3f-4747-9783-445604b0a1d4",
    "createdAt": "2025-11-27T18:31:24.594451"
  },
  {
    "firstName": "test",
    "lastName": "user",
    "email": "test@user.com",
    "password": "password",
    "companyName": "New",
    "id": "a5d53494-35d5-47ef-9790-e0c4f45f5711",
    "createdAt": "2025-11-27T18:33:47.6338682"
  },
  {
    "firstName": "test",
    "lastName": "user",
    "email": "test@user.com",
    "password": "password",
    "companyName": "new",
    "id": "3291758e-9b28-49ea-8ae3-1b59423a6b20",
    "createdAt": "2025-11-27T18:47:06.573967"
  },
  {
    "firstName": "test",
    "lastName": "user",
    "email": "test@user.com",
    "password": "password",
    "companyName": "new",
    "id": "432ac362-e4d9-46b5-8293-c357aeb34428",
    "createdAt": "2025-11-27T19:46:31.1260272"
  },
  {
    "firstName": "test",
    "lastName": "case",
    "email": "test@case.com",
    "password": "password",
    "companyName": "new",
    "id": "947e0045-b112-4afe-8f26-9c19d9ea56ff",
    "createdAt": "2025-11-27T20:18:08.6509787"
  },
  {
    "firstName": "test",
    "lastName": "user",
    "email": "test@user.com",
    "password": "password",
    "companyName": "new",
    "id": "b2eca625-3330-47b9-9129-8eb04852ea10",
    "createdAt": "2025-11-27T20:40:34.5171799"
  },
  {
    "firstName": "test",
    "lastName": "user",
    "email": "test@user.com",
    "password": "password",
    "companyName": "new",
    "id": "a97f3a26-eae4-456e-9c1e-3eaa927004e2",
    "createdAt": "2025-11-27T21:07:56.5941058"
  },
  {
    "firstName": "test",
    "lastName": "case",
    "email": "test@case.com",
    "password": "password",
    "companyName": "new",
    "id": "234d660f-8fe8-46a6-8558-8f6d3837b55e",
    "createdAt": "2025-11-27T21:55:56.542014"
  },
  {
    "firstName": "test",
    "lastName": "case",
    "email": "test@case.com",
    "password": "password",
    "companyName": "new",
    "id": "94e7d741-0e4e-449a-a383-cf743985c836",
    "createdAt": "2025-11-27T22:19:24.3194063"
  },
  {
    "firstName": "test",
    "lastName": "case",
    "email": "test@case.com",
    "password": "password",
    "companyName": "new",
    "id": "549dd4fe-d767-48ad-b473-06bdf56da87f",
    "createdAt": "2025-11-27T22:44:32.3620493"
  },
  {
    "firstName": "test",
    "lastName": "company",
    "email": "test@company.com",
    "password": "password",
    "companyName": "new",
    "id": "e2718d78-12ce-42e4-8e11-7136edd6593a",
    "createdAt": "2025-11-27T23:10:42.8889937"
  },
  {
    "firstName": "test",
    "lastName": "company",
    "email": "test@company.com",
    "password": "password",
    "companyName": "new",
    "id": "b07b446e-7520-41a1-a369-291afab75801",
    "createdAt": "2025-11-27T23:15:49.6162014"
  },
  {
    "firstName": "test",
    "lastName": "company",
    "email": "test@company.com",
    "password": "password",
    "companyName": "new",
    "id": "d5e1a347-f2dd-4dd1-9312-7f7d3e50f499",
    "createdAt": "2025-11-27T23:24:20.2929005"
  },
  {
    "firstName": "test",
    "lastName": "company",
    "email": "test@company.com",
    "password": "password",
    "companyName": "new",
    "id": "71229511-0ab6-401b-a2bd-156f6dca4cce",
    "createdAt": "2025-11-27T23:33:07.4536592"
  },
  {
    "firstName": "test",
    "lastName": "company",
    "email": "test@company.com",
    "password": "password",
    "companyName": "new",
    "id": "b032c3e8-c180-49ac-bbb0-23bd8efd72af",
    "createdAt": "2025-11-28T07:40:47.0666068"
  },
  {
    "firstName": "test",
    "lastName": "company",
    "email": "test@company.com",
    "password": "password",
    "companyName": "new",
    "id": "db20a4ee-8812-4fd7-846e-a902f5cc6de8",
    "createdAt": "2025-11-28T07:47:24.1435651"
  },
  {
    "firstName": "test",
    "lastName": "company",
    "email": "test@company.com",
    "password": "password",
    "companyName": "new",
    "id": "50013111-20a7-4cdc-8275-04e1db56b5d2",
    "createdAt": "2025-11-28T07:51:56.0897675"
  },
  {
    "firstName": "test",
    "lastName": "company",
    "email": "test@company",
    "password": "password",
    "companyName": "new",
    "id": "4b3276b5-32c4-48eb-b85d-4895d2c5e022",
    "createdAt": "2025-11-28T07:57:06.7033132"
  },
  {
    "firstName": "test",
    "lastName": "company",
    "email": "test@company.com",
    "password": "password",
    "companyName": "new",
    "id": "96a4e85f-a6f9-4a52-a242-c95e44d51f84",
    "createdAt": "2025-11-28T15:04:19.1442664"
  },
  {
    "firstName": "test",
    "lastName": "case",
    "email": "test@case.com",
    "password": "password",
    "companyName": "new",
    "id": "b4e70195-1c26-4442-8331-ead8e920b5c0",
    "createdAt": "2025-11-28T15:17:24.3819081"
  },
  {
    "firstName": "test",
    "lastName": "case",
    "email": "test@case.com",
    "password": "password",
    "companyName": "new",
    "id": "7f3c4a7e-a92d-45ba-bf06-3d3bc28a1875",
    "createdAt": "2025-11-28T15:25:53.7756314"
  },
  {
    "firstName": "test",
    "lastName": "case",
    "email": "test@case.com",
    "password": "password",
    "companyName": "new",
    "id": "a7dce776-0464-430e-87ff-e7513ad781be",
    "createdAt": "2025-11-28T15:53:57.2350587"
  }
]